setup.py
abdalla_dsnd_distributions/Binomialdistribution.py
abdalla_dsnd_distributions/Gaussiandistribution.py
abdalla_dsnd_distributions/Generaldistribution.py
abdalla_dsnd_distributions/__init__.py
abdalla_dsnd_distributions.egg-info/PKG-INFO
abdalla_dsnd_distributions.egg-info/SOURCES.txt
abdalla_dsnd_distributions.egg-info/dependency_links.txt
abdalla_dsnd_distributions.egg-info/not-zip-safe
abdalla_dsnd_distributions.egg-info/top_level.txt